setup.py
kannanpackage/Binomialdistribution.py
kannanpackage/Gaussiandistribution.py
kannanpackage/Generaldistribution.py
kannanpackage/__init__.py
kannanpackage.egg-info/PKG-INFO
kannanpackage.egg-info/SOURCES.txt
kannanpackage.egg-info/dependency_links.txt
kannanpackage.egg-info/not-zip-safe
kannanpackage.egg-info/top_level.txt