Metadata-Version: 1.0
Name: kannanpackage
Version: 0.2
Summary: Gaussian distributions
Home-page: UNKNOWN
Author: Abhijith
Author-email: akgamer077@gmail.com
License: UNKNOWN
Platform: UNKNOWN
